wivi-graph-lib/__init__.py
wivi-graph-lib/client.py
wivi-graph-lib/configuration.py
wivi-graph-lib/device_connection.py
wivi-graph-lib/device_info.py
wivi-graph-lib/device_status.py
wivi-graph-lib/device_version.py
wivi-graph-lib/dtc.py
wivi-graph-lib/ecu.py
wivi-graph-lib/fail_processing.py
wivi-graph-lib/formula.py
wivi-graph-lib/gps.py
wivi-graph-lib/main.py
wivi-graph-lib/message.py
wivi-graph-lib/network.py
wivi-graph-lib/network_stats.py
wivi-graph-lib/signal.py
wivi-graph-lib/test_configuration.py
wivi-graph-lib/test_device_connection.py
wivi-graph-lib/test_device_version.py
wivi-graph-lib/test_dtc.py
wivi-graph-lib/test_fail_processing.py
wivi-graph-lib/test_gps.py
wivi-graph-lib/test_message.py
wivi-graph-lib/test_network_stats.py
wivi-graph-lib/test_signal.py
wivi-graph-lib/version.py
wivi_graph_client_py/__init__.py
wivi_graph_client_py/client.py
wivi_graph_client_py/configuration.py
wivi_graph_client_py/device_connection.py
wivi_graph_client_py/device_info.py
wivi_graph_client_py/device_status.py
wivi_graph_client_py/device_version.py
wivi_graph_client_py/dtc.py
wivi_graph_client_py/ecu.py
wivi_graph_client_py/fail_processing.py
wivi_graph_client_py/formula.py
wivi_graph_client_py/gps.py
wivi_graph_client_py/main.py
wivi_graph_client_py/message.py
wivi_graph_client_py/network.py
wivi_graph_client_py/network_stats.py
wivi_graph_client_py/signal.py
wivi_graph_client_py/test_configuration.py
wivi_graph_client_py/test_device_connection.py
wivi_graph_client_py/test_device_version.py
wivi_graph_client_py/test_dtc.py
wivi_graph_client_py/test_fail_processing.py
wivi_graph_client_py/test_gps.py
wivi_graph_client_py/test_message.py
wivi_graph_client_py/test_network_stats.py
wivi_graph_client_py/test_signal.py
wivi_graph_client_py/version.py
wivi_graph_lib-2.2.4.dist-info/METADATA
wivi_graph_lib-2.2.4.dist-info/WHEEL
wivi_graph_lib-2.2.4.dist-info/top_level.txt
wivi_graph_lib-2.2.4.dist-info/RECORD
